pysyncon/__init__.py
pysyncon/augsynth.py
pysyncon/base.py
pysyncon/dataprep.py
pysyncon/generator.py
pysyncon/inference.py
pysyncon/penalized.py
pysyncon/robust.py
pysyncon/synth.py
pysyncon/utils.py
pysyncon-1.5.2.dist-info/LICENSE
pysyncon-1.5.2.dist-info/METADATA
pysyncon-1.5.2.dist-info/WHEEL
pysyncon-1.5.2.dist-info/top_level.txt
pysyncon-1.5.2.dist-info/RECORD
