Metadata-Version: 2.1
Name: pysyncon
Version: 1.5.2
Home-page: https://github.com/sdfordham/pysyncon/
Author: Stiofán Fordham
License: MIT License
Keywords: Synth,augsynth,synthetic-control-method,causal-inference
Requires-Python: >=3.8
License-File: LICENSE
Requires-Dist: numpy>=1.24.0
Requires-Dist: matplotlib>=3.6.2
Requires-Dist: pandas>=1.5.2
Requires-Dist: scipy>=1.9.3
Provides-Extra: dev
Requires-Dist: black==23.10.1; extra == "dev"
